// class version 55.0 (55)
// access flags 0x21
public class org/example/generic/lib/server/Responses {

  // compiled from: Responses.java

  // access flags 0x0
  // signature Lorg/example/generic/lib/server/GenericResponse<Ljava/lang/Integer;>;
  // declaration: resInt extends org.example.generic.lib.server.GenericResponse<java.lang.Integer>
  Lorg/example/generic/lib/server/GenericResponse; resInt

  // access flags 0x0
  // signature Lorg/example/generic/lib/server/GenericResponse<Lorg/example/generic/lib/server/GenericResponse<Ljava/lang/Integer;>;>;
  // declaration: resRes extends org.example.generic.lib.server.GenericResponse<org.example.generic.lib.server.GenericResponse<java.lang.Integer>>
  Lorg/example/generic/lib/server/GenericResponse; resRes

  // access flags 0x0
  // signature Lorg/example/generic/lib/server/GenericResponse<Ljava/lang/String;>;
  // declaration: resString extends org.example.generic.lib.server.GenericResponse<java.lang.String>
  Lorg/example/generic/lib/server/GenericResponse; resString

  // access flags 0x1
  public <init>()V
   L0
    LINENUMBER 3 L0
    ALOAD 0
    INVOKESPECIAL java/lang/Object.<init> ()V
   L1
    LINENUMBER 5 L1
    ALOAD 0
    NEW org/example/generic/lib/server/GenericResponse
    DUP
    ICONST_1
    INVOKESTATIC java/lang/Integer.valueOf (I)Ljava/lang/Integer;
    INVOKESPECIAL org/example/generic/lib/server/GenericResponse.<init> (Ljava/lang/Object;)V
    PUTFIELD org/example/generic/lib/server/Responses.resInt : Lorg/example/generic/lib/server/GenericResponse;
   L2
    LINENUMBER 6 L2
    ALOAD 0
    NEW org/example/generic/lib/server/GenericResponse
    DUP
    ALOAD 0
    GETFIELD org/example/generic/lib/server/Responses.resInt : Lorg/example/generic/lib/server/GenericResponse;
    INVOKESPECIAL org/example/generic/lib/server/GenericResponse.<init> (Ljava/lang/Object;)V
    PUTFIELD org/example/generic/lib/server/Responses.resRes : Lorg/example/generic/lib/server/GenericResponse;
   L3
    LINENUMBER 7 L3
    ALOAD 0
    NEW org/example/generic/lib/server/GenericResponse
    DUP
    LDC "Oh, no!"
    INVOKESPECIAL org/example/generic/lib/server/GenericResponse.<init> (Ljava/lang/String;)V
    PUTFIELD org/example/generic/lib/server/Responses.resString : Lorg/example/generic/lib/server/GenericResponse;
    RETURN
   L4
    LOCALVARIABLE this Lorg/example/generic/lib/server/Responses; L0 L4 0
    MAXSTACK = 4
    MAXLOCALS = 1
}
